{
  "fullNodeVersion": "v2.11.0",
  "compilerOptionsUsed": {
    "ignoreUnusedConstantsWarnings": true,
    "ignoreUnusedVariablesWarnings": false,
    "ignoreUnusedFieldsWarnings": false,
    "ignoreUnusedPrivateFunctionsWarnings": false,
    "ignoreUpdateFieldsCheckWarnings": false,
    "ignoreCheckExternalCallerWarnings": false
  },
  "infos": {
    "AccountBase": {
      "sourceFile": "lib/account/account_base.ral",
      "sourceCodeHash": "4ee169d6736f083d3c77a31adaa6c2ff90c8af489545d9366b66cfe11f653cb4",
      "bytecodeDebugPatch": "",
      "codeHashDebug": "",
      "warnings": []
    },
    "AccountFactory": {
      "sourceFile": "lib/account/account_factory.ral",
      "sourceCodeHash": "fda2b961b921d81e76783f970c4e049cbe607eb547c3f7dcc78ffca651d59b0e",
      "bytecodeDebugPatch": "",
      "codeHashDebug": "",
      "warnings": []
    },
    "AccountInterface": {
      "sourceFile": "lib/account/account_interface.ral",
      "sourceCodeHash": "2b9201d845a816cedf4340cd394ba73962d202e10552d6ce006602059f97cf2d",
      "bytecodeDebugPatch": "",
      "codeHashDebug": "",
      "warnings": []
    },
    "ApadToken": {
      "sourceFile": "apad_token.ral",
      "sourceCodeHash": "4e1ae5f957992dd7bda54ea94b7dfabc551fb994d5919605dc5b0cc9e712b521",
      "bytecodeDebugPatch": "",
      "codeHashDebug": "da7543ebc9e29ae7fe1d75043dedead5564b44998b4f5076c4eee829bc814ca3",
      "warnings": []
    },
    "ApadTokenBurnTX": {
      "sourceFile": "apad_token.ral",
      "sourceCodeHash": "4e1ae5f957992dd7bda54ea94b7dfabc551fb994d5919605dc5b0cc9e712b521",
      "bytecodeDebugPatch": "",
      "codeHashDebug": "",
      "warnings": []
    },
    "DexPoolInterface": {
      "sourceFile": "external/dex_pool_interface.ral",
      "sourceCodeHash": "3ea6d07567c867e3643a35c2a1d527f75922e690af8f968b7ce39eb51261f0ea",
      "bytecodeDebugPatch": "",
      "codeHashDebug": "",
      "warnings": []
    },
    "DummyToken": {
      "sourceFile": "external/dummy/dummy_token.ral",
      "sourceCodeHash": "dab2da72108949e6012451d4c20b11001b2f6b524a9d03487880bc97336cc9e2",
      "bytecodeDebugPatch": "",
      "codeHashDebug": "a2800413eb2c5c23d48068db23df5f8eeaba04653e12c8ed59d589720d96dadd",
      "warnings": []
    },
    "IFungibleToken": {
      "sourceFile": "../node_modules/@alephium/web3/std/fungible_token_interface.ral",
      "sourceCodeHash": "6809cb06fb20fa7edf529461998beeebd12b1636d439612cca2f84214dbf4a20",
      "bytecodeDebugPatch": "",
      "codeHashDebug": "",
      "warnings": []
    },
    "IUpgradable": {
      "sourceFile": "lib/upgradable/iupgradable.ral",
      "sourceCodeHash": "10ef8b407563017824792123ea30f599b8f31edf2dc4e4d35c39482677653f05",
      "bytecodeDebugPatch": "",
      "codeHashDebug": "",
      "warnings": []
    },
    "IUpgradableChangeOwnerApplyTX": {
      "sourceFile": "lib/upgradable/iupgradable.ral",
      "sourceCodeHash": "10ef8b407563017824792123ea30f599b8f31edf2dc4e4d35c39482677653f05",
      "bytecodeDebugPatch": "",
      "codeHashDebug": "",
      "warnings": []
    },
    "IUpgradableChangeOwnerTX": {
      "sourceFile": "lib/upgradable/iupgradable.ral",
      "sourceCodeHash": "10ef8b407563017824792123ea30f599b8f31edf2dc4e4d35c39482677653f05",
      "bytecodeDebugPatch": "",
      "codeHashDebug": "",
      "warnings": []
    },
    "IUpgradableMigrateApplyTX": {
      "sourceFile": "lib/upgradable/iupgradable.ral",
      "sourceCodeHash": "10ef8b407563017824792123ea30f599b8f31edf2dc4e4d35c39482677653f05",
      "bytecodeDebugPatch": "",
      "codeHashDebug": "",
      "warnings": []
    },
    "IUpgradableMigrateTX": {
      "sourceFile": "lib/upgradable/iupgradable.ral",
      "sourceCodeHash": "10ef8b407563017824792123ea30f599b8f31edf2dc4e4d35c39482677653f05",
      "bytecodeDebugPatch": "",
      "codeHashDebug": "",
      "warnings": []
    },
    "IUpgradableMigrateWithFieldsApplyTX": {
      "sourceFile": "lib/upgradable/iupgradable.ral",
      "sourceCodeHash": "10ef8b407563017824792123ea30f599b8f31edf2dc4e4d35c39482677653f05",
      "bytecodeDebugPatch": "",
      "codeHashDebug": "",
      "warnings": []
    },
    "IUpgradableMigrateWithFieldsTX": {
      "sourceFile": "lib/upgradable/iupgradable.ral",
      "sourceCodeHash": "10ef8b407563017824792123ea30f599b8f31edf2dc4e4d35c39482677653f05",
      "bytecodeDebugPatch": "",
      "codeHashDebug": "",
      "warnings": []
    },
    "IUpgradableResetUpgradeTX": {
      "sourceFile": "lib/upgradable/iupgradable.ral",
      "sourceCodeHash": "10ef8b407563017824792123ea30f599b8f31edf2dc4e4d35c39482677653f05",
      "bytecodeDebugPatch": "",
      "codeHashDebug": "",
      "warnings": []
    },
    "MerkleProof": {
      "sourceFile": "lib/merkle_proof.ral",
      "sourceCodeHash": "77d1b1344f92f333e9687c0b381407d9e1c94a3b45caeff4f167ae0ae99b745f",
      "bytecodeDebugPatch": "",
      "codeHashDebug": "",
      "warnings": []
    },
    "RewardDistributor": {
      "sourceFile": "rewards/reward_distributor.ral",
      "sourceCodeHash": "b69082d76bc60f38b49d7e895f87845faf39c562f97109d4890653b4f0132e69",
      "bytecodeDebugPatch": "",
      "codeHashDebug": "606b7c84b055cc1b9fb7c6242e5790129f79ae228b3778bd533b23f2474d87a8",
      "warnings": []
    },
    "RewardDistributorAddRewardsTX": {
      "sourceFile": "rewards/reward_distributor.ral",
      "sourceCodeHash": "b69082d76bc60f38b49d7e895f87845faf39c562f97109d4890653b4f0132e69",
      "bytecodeDebugPatch": "",
      "codeHashDebug": "",
      "warnings": []
    },
    "RewardDistributorHarvestTX": {
      "sourceFile": "rewards/reward_distributor.ral",
      "sourceCodeHash": "b69082d76bc60f38b49d7e895f87845faf39c562f97109d4890653b4f0132e69",
      "bytecodeDebugPatch": "",
      "codeHashDebug": "",
      "warnings": []
    },
    "SaleBase": {
      "sourceFile": "launch_sale/generic/sale_base.ral",
      "sourceCodeHash": "9dabc8c9877fd97c2cfb29dc6d0f617f7bb965519b0009fe96efad9afb43cf63",
      "bytecodeDebugPatch": "",
      "codeHashDebug": "",
      "warnings": []
    },
    "SaleBuyerAccount": {
      "sourceFile": "launch_sale/generic/sale_buyer_account.ral",
      "sourceCodeHash": "f12ede41067974ef7d977ab49bf308e629d44abf12c13e311730c339edbe28b8",
      "bytecodeDebugPatch": "",
      "codeHashDebug": "5b85bbcf941c0e29fa634eccc5c21a0545245218348b1c27c9c7fc3980f5913a",
      "warnings": []
    },
    "SaleFlatPrice": {
      "sourceFile": "launch_sale/sale_flat_price.ral",
      "sourceCodeHash": "ad9194bb4e1956e6b233a4e6646f1b43cfda440fe6ab726d605c6a8cefa971bb",
      "bytecodeDebugPatch": "",
      "codeHashDebug": "",
      "warnings": []
    },
    "SaleFlatPriceAlph": {
      "sourceFile": "launch_sale/sale_flat_price_alph.ral",
      "sourceCodeHash": "fdcf903b00f84e62547297224070a1035e2d9a52cba5339b4b1388201aff1b91",
      "bytecodeDebugPatch": "",
      "codeHashDebug": "b017759f9a30ec96d21081b982dd0c24e1d59a4ecbe4b598e7f4d4ddde3b14b8",
      "warnings": []
    },
    "SaleFlatPriceAlphBuyTX": {
      "sourceFile": "launch_sale/sale_flat_price_alph.ral",
      "sourceCodeHash": "fdcf903b00f84e62547297224070a1035e2d9a52cba5339b4b1388201aff1b91",
      "bytecodeDebugPatch": "",
      "codeHashDebug": "",
      "warnings": []
    },
    "SaleFlatPriceAlphClaimRefundTX": {
      "sourceFile": "launch_sale/sale_flat_price_alph.ral",
      "sourceCodeHash": "fdcf903b00f84e62547297224070a1035e2d9a52cba5339b4b1388201aff1b91",
      "bytecodeDebugPatch": "",
      "codeHashDebug": "",
      "warnings": []
    },
    "SaleFlatPriceAlphClaimTX": {
      "sourceFile": "launch_sale/sale_flat_price_alph.ral",
      "sourceCodeHash": "fdcf903b00f84e62547297224070a1035e2d9a52cba5339b4b1388201aff1b91",
      "bytecodeDebugPatch": "",
      "codeHashDebug": "",
      "warnings": []
    },
    "SaleFlatPriceAlphSetMerkleRootTX": {
      "sourceFile": "launch_sale/sale_flat_price_alph.ral",
      "sourceCodeHash": "fdcf903b00f84e62547297224070a1035e2d9a52cba5339b4b1388201aff1b91",
      "bytecodeDebugPatch": "",
      "codeHashDebug": "",
      "warnings": []
    },
    "SaleManager": {
      "sourceFile": "launch_sale/sale_manager.ral",
      "sourceCodeHash": "4fca9808d897c1799824fa09c7ad2ee7862533708da28ad71407cbc96d0529f8",
      "bytecodeDebugPatch": "",
      "codeHashDebug": "ea24ab6940736196666e9ee716a14ebb3eaa40d4fb1c679702afd24415597647",
      "warnings": []
    },
    "SaleManagerCreateSaleFlatPriceTX": {
      "sourceFile": "launch_sale/sale_manager.ral",
      "sourceCodeHash": "4fca9808d897c1799824fa09c7ad2ee7862533708da28ad71407cbc96d0529f8",
      "bytecodeDebugPatch": "",
      "codeHashDebug": "",
      "warnings": []
    },
    "Staking": {
      "sourceFile": "rewards/staking.ral",
      "sourceCodeHash": "5d20604a5113f125b24b8d7994e6b1ef8d65df248211aa74a34551d0f1529c3d",
      "bytecodeDebugPatch": "",
      "codeHashDebug": "09cfa395376389a28fa1b847641fcef1d5909d2dccef2b581cb05d87d697bf83",
      "warnings": []
    },
    "StakingAccount": {
      "sourceFile": "rewards/staking_account.ral",
      "sourceCodeHash": "2dfdfad9239116ad6be87d166434979414c427a3b398c797a346df8a94f8cdd8",
      "bytecodeDebugPatch": "",
      "codeHashDebug": "d2ab403cff492d8c50da5f47d4865f9cc988f47fa05a01d6a2a3d94b1b3c1e71",
      "warnings": []
    },
    "StakingClaimRewardsTX": {
      "sourceFile": "rewards/staking.ral",
      "sourceCodeHash": "5d20604a5113f125b24b8d7994e6b1ef8d65df248211aa74a34551d0f1529c3d",
      "bytecodeDebugPatch": "",
      "codeHashDebug": "",
      "warnings": []
    },
    "StakingClaimTX": {
      "sourceFile": "rewards/staking.ral",
      "sourceCodeHash": "5d20604a5113f125b24b8d7994e6b1ef8d65df248211aa74a34551d0f1529c3d",
      "bytecodeDebugPatch": "",
      "codeHashDebug": "",
      "warnings": []
    },
    "StakingDepositRewardsTX": {
      "sourceFile": "rewards/staking.ral",
      "sourceCodeHash": "5d20604a5113f125b24b8d7994e6b1ef8d65df248211aa74a34551d0f1529c3d",
      "bytecodeDebugPatch": "",
      "codeHashDebug": "",
      "warnings": []
    },
    "StakingStakeTX": {
      "sourceFile": "rewards/staking.ral",
      "sourceCodeHash": "5d20604a5113f125b24b8d7994e6b1ef8d65df248211aa74a34551d0f1529c3d",
      "bytecodeDebugPatch": "",
      "codeHashDebug": "",
      "warnings": []
    },
    "StakingUnstakeTX": {
      "sourceFile": "rewards/staking.ral",
      "sourceCodeHash": "5d20604a5113f125b24b8d7994e6b1ef8d65df248211aa74a34551d0f1529c3d",
      "bytecodeDebugPatch": "",
      "codeHashDebug": "",
      "warnings": []
    },
    "TestUpgradable": {
      "sourceFile": "lib/dummy/test_upgradable.ral",
      "sourceCodeHash": "7964616cee2174c898a54cb97ff65b81c300d6eddd0c4a3be3dcf64a38176be5",
      "bytecodeDebugPatch": "",
      "codeHashDebug": "9bf3009274456447b20ea932f5eb747e867b0977f8fb910075616925a3fb4c7e",
      "warnings": []
    },
    "TestUpgradableV2": {
      "sourceFile": "lib/dummy/test_upgradable_v2.ral",
      "sourceCodeHash": "06af2fae1d0104dc00bc90af8cfa8ed10b009c3f550202b70a4776ff7139be1e",
      "bytecodeDebugPatch": "",
      "codeHashDebug": "acb86f28101a38a11d92aaad09ec4e4af2367ef7b61c319b28075d321677b0d5",
      "warnings": []
    },
    "TokenPair": {
      "sourceFile": "external/dummy/token_pair.ral",
      "sourceCodeHash": "bc3f5d5bdd389d7225a46a48969cb1adcc2ed06b5a07f95a789eecbc54b961bd",
      "bytecodeDebugPatch": "",
      "codeHashDebug": "d663548c102e2428a76913803835cada6a2e98b7c5a1735577b0137fb75f6542",
      "warnings": []
    },
    "Upgradable": {
      "sourceFile": "lib/upgradable/upgradable.ral",
      "sourceCodeHash": "6bc4b1ebca2769f444417809861be3504f7735b06a94ef9b1e7d3207014162ed",
      "bytecodeDebugPatch": "",
      "codeHashDebug": "",
      "warnings": []
    }
  }
}